remoshock/application/cli.py
remoshock/application/randomizer.py
remoshock/application/server.py
remoshock/core/action.py
remoshock/core/config.py
remoshock/core/receiverproperties.py
remoshock/core/remoshock.py
remoshock/core/version.py
remoshock/httpserver/filehandler.py
remoshock/httpserver/httpserver.py
remoshock/httpserver/requesthandler.py
remoshock/httpserver/resthandler.py
remoshock/receiver/arshock.py
remoshock/receiver/dogtra.py
remoshock/receiver/pac.py
remoshock/receiver/patpett150.py
remoshock/receiver/pawanti.py
remoshock/receiver/petrainer.py
remoshock/receiver/receiver.py
remoshock/receiver/wodondog.py
remoshock/receiver/wodondogb.py
remoshock/scheduler/commandtask.py
remoshock/scheduler/periodictask.py
remoshock/scheduler/scheduler.py
remoshock/scheduler/task.py
remoshock/sdr/sdrsender.py
remoshock/sdr/urhcli.py
remoshock/sdr/urhinternal.py
remoshock/util/logutil.py
remoshock/util/powermanager.py
remoshock/web/favicon.png
remoshock/web/index.html
remoshock/web/manifest.json
remoshock/web/admin/admin.html
remoshock/web/admin/admin.js
remoshock/web/admin/log.css
remoshock/web/admin/log.html
remoshock/web/admin/log.js
remoshock/web/auth/auth.js
remoshock/web/auth/index.html
remoshock/web/debug/debug.css
remoshock/web/debug/debug.js
remoshock/web/debug/index.html
remoshock/web/gamepad/gamepad.css
remoshock/web/gamepad/gamepad.js
remoshock/web/gamepad/index.html
remoshock/web/gamepad/mapping.html
remoshock/web/gamepad/mapping.js
remoshock/web/gamepad/ruleset.js
remoshock/web/gamepad/simon-ruleset.js
remoshock/web/gamepad/userinterface.js
remoshock/web/gamepad/walk-ruleset.js
remoshock/web/randomizer/index.html
remoshock/web/randomizer/randomizer.css
remoshock/web/randomizer/randomizer.js
remoshock/web/remote/index.html
remoshock/web/remote/remote.css
remoshock/web/remote/remote.js
remoshock/web/resources/logo-128.png
remoshock/web/resources/logo-64.png
remoshock/web/resources/logo.xcf
remoshock/web/resources/remoshock.js
remoshock-0.84.dist-info/licenses/docs/LICENSE.md
remoshock-0.84.dist-info/METADATA
remoshock-0.84.dist-info/WHEEL
remoshock-0.84.dist-info/entry_points.txt
remoshock-0.84.dist-info/top_level.txt
remoshock-0.84.dist-info/RECORD
