Metadata-Version: 2.4
Name: remoshock
Version: 0.84
Summary: Computer based shock-collar remote control with "evil" features.
Home-page: https://remoshock.github.io
Author: Nils Winter
Author-email: nils.winter@yahoo.com
License: GNU Affero General Public License v3 (AGPL)
Classifier: Programming Language :: Python :: 3
Classifier: Operating System :: POSIX :: Linux
Requires-Python: >=3.6
License-File: docs/LICENSE.md
Requires-Dist: numpy
Requires-Dist: serial
Dynamic: author
Dynamic: author-email
Dynamic: classifier
Dynamic: description
Dynamic: description-content-type
Dynamic: home-page
Dynamic: license
Dynamic: license-file
Dynamic: requires-dist
Dynamic: requires-python
Dynamic: summary
